xj_ruoyi/__init__.py
xj_ruoyi/admin.py
xj_ruoyi/apps.py
xj_ruoyi/models.py
xj_ruoyi/urls.py
xj_ruoyi/utils/__init__.py
xj_ruoyi/utils/backends.py
xj_ruoyi/utils/core_initialize.py
xj_ruoyi/utils/custom_jwt_auth.py
xj_ruoyi/utils/custom_response.py
xj_ruoyi/utils/custom_tool.py
xj_ruoyi/utils/data_permission.py
xj_ruoyi/utils/exception.py
xj_ruoyi/utils/filters.py
xj_ruoyi/utils/git_utils.py
xj_ruoyi/utils/import_export.py
xj_ruoyi/utils/import_export_mixin.py
xj_ruoyi/utils/json_response.py
xj_ruoyi/utils/middleware.py
xj_ruoyi/utils/models.py
xj_ruoyi/utils/pagination.py
xj_ruoyi/utils/permission.py
xj_ruoyi/utils/request_util.py
xj_ruoyi/utils/serializers.py
xj_ruoyi/utils/string_util.py
xj_ruoyi/utils/swagger.py
xj_ruoyi/utils/user_wrapper.py
xj_ruoyi/utils/utility_method.py
xj_ruoyi/utils/validator.py
xj_ruoyi/utils/viewset.py
xj_ruoyi/views/__init__.py
xj_ruoyi/views/api_white_list.py
xj_ruoyi/views/dept.py
xj_ruoyi/views/menu.py
xj_ruoyi/views/menu_button.py
xj_ruoyi/views/operation_log.py
xj_ruoyi/views/post.py
xj_ruoyi/views/role.py
xj_ruoyi-1.0.0.dist-info/METADATA
xj_ruoyi-1.0.0.dist-info/WHEEL
xj_ruoyi-1.0.0.dist-info/top_level.txt
xj_ruoyi-1.0.0.dist-info/RECORD
