Metadata-Version: 2.1
Name: xj-ruoyi
Version: 1.0.0
Summary: 权限模块(若依)
License: apache 3.0
Requires-Dist: django-restql (==0.15.3)
Requires-Dist: drf-yasg (==1.21.5)
Requires-Dist: django-filter (==22.1)
Requires-Dist: djangorestframework (==3.14.0)
Requires-Dist: djangorestframework-simplejwt (==5.2.2)
Requires-Dist: user-agents
